flake8_self.py
flake8_self-0.2.2.dist-info/METADATA
flake8_self-0.2.2.dist-info/RECORD
flake8_self-0.2.2.dist-info/WHEEL
flake8_self-0.2.2.dist-info/entry_points.txt
flake8_self-0.2.2.dist-info/top_level.txt
