Metadata-Version: 2.1
Name: flake8-self
Version: 0.2.2
Summary: Private member access linting plugin for flake8.
Requires-Dist: flake8
